ornator/__init__.py
ornator/class_decorator.py
ornator/decorator.py
ornator-0.0.4.dist-info/licenses/LICENSE
ornator-0.0.4.dist-info/METADATA
ornator-0.0.4.dist-info/WHEEL
ornator-0.0.4.dist-info/top_level.txt
ornator-0.0.4.dist-info/RECORD
