Metadata-Version: 2.4
Name: Ornator
Version: 0.0.4
Summary: This library provides a robust set of decorators for enhancing Python code functionality. It includes:
Home-page: https://github.com/ConectarWali/Ornator
Author: Conectar Wali SAS
Author-email: dev@conectarwalisas.com.co
Classifier: Programming Language :: Python :: 3
Classifier: License :: Other/Proprietary License
Classifier: Operating System :: OS Independent
Requires-Python: >=3.9
License-File: LICENSE
Dynamic: author
Dynamic: author-email
Dynamic: classifier
Dynamic: description
Dynamic: description-content-type
Dynamic: home-page
Dynamic: license-file
Dynamic: requires-python
Dynamic: summary
